longjrm/__init__.py
longjrm/config/__init__.py
longjrm/config/config.py
longjrm/config/runtime.py
longjrm/connection/__init__.py
longjrm/connection/connectors.py
longjrm/connection/dbconn.py
longjrm/connection/driver_map.json
longjrm/connection/driver_registry.py
longjrm/connection/dsn_parts_helper.py
longjrm/connection/pool.py
longjrm/database/__init__.py
longjrm/database/db.py
longjrm/database/db2.py
longjrm/database/generic.py
longjrm/database/mysql.py
longjrm/database/oracle.py
longjrm/database/placeholder_handler.py
longjrm/database/postgres.py
longjrm/database/spark.py
longjrm/database/sqlite.py
longjrm/database/sqlserver.py
longjrm/tests/bulk_load_test.py
longjrm/tests/connection_test.py
longjrm/tests/delete_test.py
longjrm/tests/insert_test.py
longjrm/tests/merge_test.py
longjrm/tests/pool_test.py
longjrm/tests/script_test.py
longjrm/tests/select_test.py
longjrm/tests/spark_test.py
longjrm/tests/stream_test.py
longjrm/tests/test_utils.py
longjrm/tests/transaction_test.py
longjrm/tests/update_test.py
longjrm/utils/__init__.py
longjrm/utils/data.py
longjrm/utils/sql.py
longjrm-0.1.1.dist-info/licenses/LICENSE
longjrm-0.1.1.dist-info/METADATA
longjrm-0.1.1.dist-info/WHEEL
longjrm-0.1.1.dist-info/top_level.txt
longjrm-0.1.1.dist-info/RECORD
