Metadata-Version: 2.4
Name: longjrm
Version: 0.1.1
Summary: JRM Library for Python
Author: Mike Gong at LONGINFO
Author-email: Mike Gong at LONGINFO <gongmike@gmail.com>
License: Apache-2.0
Project-URL: Homepage, https://github.com/mikegong/longjrm-py
Project-URL: Bug Tracker, https://github.com/mikegong/longjrm-py/issues
Classifier: Development Status :: 3 - Alpha
Classifier: Intended Audience :: Developers
Classifier: Programming Language :: Python :: 3
Classifier: Programming Language :: Python :: 3.10
Classifier: Programming Language :: Python :: 3.11
Classifier: Programming Language :: Python :: 3.12
Requires-Python: >=3.10
License-File: LICENSE
Requires-Dist: DBUtils>=3.0.3
Requires-Dist: cryptography>=41.0.0
Provides-Extra: mysql
Requires-Dist: PyMySQL>=1.1.0; extra == "mysql"
Provides-Extra: postgres
Requires-Dist: psycopg[binary]>=3.1.0; extra == "postgres"
Provides-Extra: oracle
Requires-Dist: oracledb>=2.0.0; extra == "oracle"
Provides-Extra: sqlserver
Requires-Dist: pyodbc>=4.0.39; extra == "sqlserver"
Provides-Extra: db2
Requires-Dist: ibm_db>=3.2.0; extra == "db2"
Provides-Extra: spark
Requires-Dist: pyspark>=3.3.0; extra == "spark"
Requires-Dist: delta-spark>=2.3.0; extra == "spark"
Provides-Extra: sqlalchemy
Requires-Dist: SQLAlchemy>=2.0.0; extra == "sqlalchemy"
Provides-Extra: all
Requires-Dist: PyMySQL>=1.1.0; extra == "all"
Requires-Dist: psycopg[binary]>=3.1.0; extra == "all"
Requires-Dist: oracledb>=2.0.0; extra == "all"
Requires-Dist: pyodbc>=4.0.39; extra == "all"
Requires-Dist: ibm_db>=3.2.0; extra == "all"
Requires-Dist: ibm-db-sa>=0.4.0; extra == "all"
Requires-Dist: pyspark>=3.3.0; extra == "all"
Requires-Dist: delta-spark>=2.3.0; extra == "all"
Requires-Dist: SQLAlchemy>=2.0.0; extra == "all"
Provides-Extra: dev
Requires-Dist: pytest>=7.0.0; extra == "dev"
Requires-Dist: pytest-cov>=4.0.0; extra == "dev"
Dynamic: author
Dynamic: license-file
Dynamic: requires-python
